LICENSE.txt
MANIFEST.in
README.md
setup.cfg
setup.py
kedro_fast_api/__init__.py
kedro_fast_api/api_factory.py
kedro_fast_api/dockerfile_generator.py
kedro_fast_api/init_files.py
kedro_fast_api/plugin.py
kedro_fast_api/utils.py
kedro_fast_api.egg-info/PKG-INFO
kedro_fast_api.egg-info/SOURCES.txt
kedro_fast_api.egg-info/dependency_links.txt
kedro_fast_api.egg-info/entry_points.txt
kedro_fast_api.egg-info/not-zip-safe
kedro_fast_api.egg-info/requires.txt
kedro_fast_api.egg-info/top_level.txt
kedro_fast_api/docker_files/.dockerignore
kedro_fast_api/docker_files/Dockerfile
kedro_fast_api/docker_files/create_credentials_in_kedro.py
kedro_fast_api/init_files/api.yml
kedro_fast_api/init_files/catalog.yml
kedro_fast_api/init_files/api_pipeline/__init__.py
kedro_fast_api/init_files/api_pipeline/nodes.py
kedro_fast_api/init_files/api_pipeline/pipeline.py
kedro_fast_api/models/__init__.py
kedro_fast_api/models/config.py
kedro_fast_api/models/config_parser.py
kedro_fast_api/templates/api_template.j2