Metadata-Version: 2.1
Name: kedro-fast-api
Version: 0.6.0
Summary: API to run pickle models with kedro.
Home-page: https://bitbucket.org/indiciumtech/kedro_fast_api
Author: Artur Wagner
Author-email: artur.wagner@indicium.tech
License: Apache Software License 2.0
Download-URL: https://bitbucket.org/indiciumtech/kedro_fast_api/get/master.zip
Keywords: kedro_fast_api
Platform: UNKNOWN
Classifier: Development Status :: 2 - Pre-Alpha
Classifier: Intended Audience :: Developers
Classifier: License :: OSI Approved :: Apache Software License
Classifier: Natural Language :: English
Classifier: Programming Language :: Python :: 2
Classifier: Programming Language :: Python :: 2.7
Classifier: Programming Language :: Python :: 3
Classifier: Programming Language :: Python :: 3.5
Classifier: Programming Language :: Python :: 3.6
Classifier: Programming Language :: Python :: 3.7
Classifier: Programming Language :: Python :: 3.8
Requires-Python: >=2.7, !=3.0.*, !=3.1.*, !=3.2.*, !=3.3.*, !=3.4.*
License-File: LICENSE.txt
